freitag/releaser/__init__.py
freitag/releaser/manage.py
freitag/releaser/prerelease.py
freitag/releaser/release.py
freitag/releaser/utils.py
freitag/releaser/tests/__init__.py
freitag/releaser/tests/test_release.py
freitag/releaser/tests/test_utils.py
freitag.releaser-4.0.3.dist-info/LICENSE
freitag.releaser-4.0.3.dist-info/METADATA
freitag.releaser-4.0.3.dist-info/WHEEL
freitag.releaser-4.0.3.dist-info/entry_points.txt
freitag.releaser-4.0.3.dist-info/top_level.txt
freitag.releaser-4.0.3.dist-info/RECORD
