Metadata-Version: 2.1
Name: freitag.releaser
Version: 4.0.3
Summary: Release facilities to ease the management of buildout based projects.
Author-email: Gil Forcada Codinachs <gil.gnome@gmail.com>
License: GNU GENERAL PUBLIC LICENSE
Project-URL: Homepage, https://github.com/derFreitag/freitag.releaser/
Project-URL: Repository, https://github.com/derFreitag/freitag.releaser/
Project-URL: Issues, https://github.com/derFreitag/freitag.releaser/issues
Project-URL: Changelog, https://github.com/derFreitag/freitag.releaser/blob/main/CHANGES.md
Keywords: releasing,packaging,pypi
Classifier: Development Status :: 5 - Production/Stable
Classifier: Intended Audience :: Developers
Classifier: License :: OSI Approved :: GNU General Public License (GPL)
Classifier: Programming Language :: Python
Classifier: Programming Language :: Python :: 3
Classifier: Programming Language :: Python :: 3 :: Only
Classifier: Programming Language :: Python :: 3.11
Classifier: Programming Language :: Python :: 3.12
Classifier: Programming Language :: Python :: 3.13
Classifier: Programming Language :: Python :: Implementation :: CPython
Classifier: Topic :: Software Development :: Libraries :: Python Modules
Requires-Python: >=3.11
License-File: LICENSE
Requires-Dist: gitpython
Requires-Dist: gocept.zestreleaser.customupload
Requires-Dist: paramiko
Requires-Dist: plone.releaser
Requires-Dist: scp
Requires-Dist: setuptools
Requires-Dist: zest.releaser[recommended]
Provides-Extra: test
Requires-Dist: testfixtures; extra == "test"
